mix_api/__init__.py
mix_api/api.py
mix_api-1.0.1.dist-info/METADATA
mix_api-1.0.1.dist-info/WHEEL
mix_api-1.0.1.dist-info/top_level.txt
mix_api-1.0.1.dist-info/RECORD
