Metadata-Version: 2.1
Name: mix-api
Version: 1.0.1
Summary: Mix Coin API Python3
Home-page: https://github.com/fuoip/mix-api
Author: fuoip
Author-email: magicwheelx@gmail.com
Classifier: Programming Language :: Python :: 3
Classifier: License :: OSI Approved :: MIT License
Classifier: Operating System :: OS Independent
Requires-Python: >=3.7
Requires-Dist: aiohttp>=3.8.0
